dryad2dataverse/__init__.py
dryad2dataverse/constants.py
dryad2dataverse/exceptions.py
dryad2dataverse/handlers.py
dryad2dataverse/monitor.py
dryad2dataverse/scripts/dryadd.py
dryad2dataverse/serializer.py
dryad2dataverse/transfer.py
dryad2dataverse-0.7.10.dist-info/METADATA
dryad2dataverse-0.7.10.dist-info/WHEEL
dryad2dataverse-0.7.10.dist-info/entry_points.txt
dryad2dataverse-0.7.10.dist-info/RECORD
