Metadata-Version: 2.3
Name: dryad2dataverse
Version: 0.7.10
Summary: Utility for copying and syncing data from a Dryad data repository to a Dataverse repository
License: MIT
Keywords: Harvard Dataverse,Dataverse,research data management,data repository,Dryad,datadryad.org,dataverse.org
Author: Paul Lesack
Author-email: paul.lesack@ubc.ca
Requires-Python: >=3.9, <4
Classifier: Development Status :: 4 - Beta
Classifier: Environment :: Console
Classifier: Intended Audience :: Education
Classifier: License :: OSI Approved :: MIT License
Classifier: Programming Language :: Python :: 3
Classifier: Programming Language :: Python :: 3.9
Classifier: Programming Language :: Python :: 3.10
Classifier: Programming Language :: Python :: 3.11
Classifier: Programming Language :: Python :: 3.12
Classifier: Programming Language :: Python :: 3.13
Classifier: Topic :: Education
Classifier: Topic :: Internet :: WWW/HTTP :: Site Management
Classifier: Topic :: Utilities
Requires-Dist: certifi (>=2022.12.7)
Requires-Dist: chardet (>=3.0.4)
Requires-Dist: charset-normalizer (>=2.0.4)
Requires-Dist: idna (>=2.10.0)
Requires-Dist: pycryptodome (>=3.20.0)
Requires-Dist: pydoc-markdown (>=4.8.2,<5.0.0)
Requires-Dist: requests (>=2.26.0)
Requires-Dist: requests-toolbelt (>=0.9.1)
Requires-Dist: setuptools (>=80.8.0,<81.0.0)
Requires-Dist: urllib3 (>=2.6.1)
Project-URL: Bug Tracker, https://github.com/ubc-library-rc/dryad2dataverse/issues
Project-URL: Documentation, https://ubc-library-rc.github.io/dryad2dataverse
Project-URL: Homepage, https://ubc-library-rc.github.io/dryad2dataverse
Project-URL: Repository, https://github.com/ubc-library-rc/dryad2dataverse.git
